<?xml version="1.0" encoding="UTF-8"?>
<information>
  <db>
    <id>314</id>
    <ui>2023</ui>
    <name>Khả Lạc - Euphoria Cafeteria</name>
    <url>khalaccafe</url>
    <im>_kha-lac-euphoria-cafeteria.jpg</im>
    <im_banner>_kha-lac-euphoria-cafeteria-cover.jpg</im_banner>
    <category>15</category>
    <phone>098.987.5555</phone>
    <address>3A, Tôn Đức Thắng, Quận 1</address>
    <district>0</district>
    <district_text_vi/>
    <district_text_en/>
    <city>30</city>
    <lat>10.779658</lat>
    <lng>106.707489</lng>
    <website/>
    <about/>
    <facebook>https://www.facebook.com/khalaccafe/</facebook>
    <facebook_cover/>
    <size>1</size>
    <status>0</status>
    <fb_load_newfeed>1</fb_load_newfeed>
    <fb_load_photo>1</fb_load_photo>
    <created>1473189642</created>
  </db>
  <more>
    <about>Bring to you the American 50's lifestyle in middle of Saigon.</about>
    <whyworkus/>
  </more>
  <companybanner>_kha-lac-euphoria-cafeteria-cover.jpg</companybanner>
  <totalJob>
    <total>1</total>
    <strji>248</strji>
  </totalJob>
</information>
