<?xml version="1.0" encoding="UTF-8"?>
<information>
  <userinfo>
    <db>
      <id>3704</id>
      <email>Alicepham2802@gmail.com</email>
      <username/>
      <name>Phạm Vũ Phương Uyên</name>
      <im>3704_image.jpg</im>
      <gender>2</gender>
      <phone>01213427896</phone>
      <address>203/9 Nguyễn văn thủ quận 1 </address>
      <city>30</city>
      <dob>1996-2-28</dob>
      <type>2</type>
      <status>1</status>
      <created>1474780593</created>
      <dayleft>0</dayleft>
      <page>0</page>
      <is_received_email>0</is_received_email>
      <last_signin>1474780593</last_signin>
      <day>28</day>
      <month>2</month>
      <year>1996</year>
      <country>vn</country>
      <skype/>
      <facebook/>
      <is_newletter>0</is_newletter>
      <fb_load_newfeed>1</fb_load_newfeed>
      <fb_load_photo>1</fb_load_photo>
      <city_text_vi>Hồ Chí Minh</city_text_vi>
      <city_text_en>Ho Chi Minh City</city_text_en>
      <lat>10.788535</lat>
      <lng>106.697048</lng>
    </db>
  </userinfo>
  <education>
    <n_608>
      <id>608</id>
      <school>Kinh tế tai chính </school>
      <degrees/>
      <fieldofstudy>Kế toán </fieldofstudy>
      <from>2015</from>
      <to>2019</to>
    </n_608>
  </education>
  <user_cv>
    <db>
      <ui>3704</ui>
      <title>, thu ngân, nhân viên</title>
      <experience>1</experience>
      <category>14,15,20</category>
      <type>4,5</type>
      <level>2</level>
      <lang>vi,en</lang>
      <s1>3500000</s1>
      <salary>1</salary>
      <about>Tính cách hoà đồng ham học hỏi cầu tiến chịu khó </about>
      <skill>Có thể nghe nói lưu loát tiếng anh </skill>
      <keyword/>
    </db>
  </user_cv>
  <savedjob>
    <total>4</total>
    <strjo>107,275,279,298</strjo>
  </savedjob>
  <appliedjob>
    <total>3</total>
    <strjo>275,279,298</strjo>
  </appliedjob>
</information>
