<?xml version="1.0" encoding="UTF-8"?>
<information>
  <userinfo>
    <db>
      <id>4731</id>
      <email>yeuemnhieu113114115@yahoo.com</email>
      <username></username>
      <name>Híu Híu</name>
      <im>1058224280960820_hiu-hiu.jpg</im>
      <gender>1</gender>
      <dob>0000-00-00</dob>
      <deactive>0</deactive>
      <type>2</type>
      <status>1</status>
      <created>1475471336</created>
      <day>0</day>
      <month>0</month>
      <year>0</year>
    </db>
  </userinfo>
</information>
