<?xml version="1.0" encoding="UTF-8"?>
<information>
  <userinfo>
    <db>
      <id>4818</id>
      <email>vananhvuong148@gmail.com</email>
      <username/>
      <name>Vương Thị Vân Anh</name>
      <im>537417759786485_van-anhh.jpg</im>
      <gender>2</gender>
      <dob>2001-8-14</dob>
      <deactive>0</deactive>
      <type>2</type>
      <status>1</status>
      <created>1475508222</created>
      <day>14</day>
      <month>8</month>
      <year>2001</year>
      <last_signin>1475508222</last_signin>
      <phone>01299998178</phone>
      <address>490/43/1 Lý Thái Tổ Phường 10 Quận 10</address>
      <country>vn</country>
      <city>30</city>
      <skype/>
      <facebook/>
      <is_newletter>0</is_newletter>
      <is_received_email>0</is_received_email>
      <fb_load_newfeed>1</fb_load_newfeed>
      <fb_load_photo>1</fb_load_photo>
      <city_text_vi>Hồ Chí Minh</city_text_vi>
      <city_text_en>Ho Chi Minh City</city_text_en>
      <lat>10.7688089</lat>
      <lng>106.671859</lng>
    </db>
  </userinfo>
  <user_cv>
    <db>
      <ui>4818</ui>
      <title>Nhân viên phục vụ </title>
      <experience>7</experience>
      <category>15,17,27,28,31,35</category>
      <type>2</type>
      <level>1</level>
      <lang>vi</lang>
      <s1>3000000</s1>
      <salary>1</salary>
      <about>Lớp 10 CV - THPT Nguyễn Thượng Hiền&#13;
Năng nổ, tích cực, chăm chỉ, trách nhiệm&#13;
</about>
      <skill>Giao tiếp tốt, nắm bắt được tâm lý khách hàng</skill>
      <keyword/>
    </db>
  </user_cv>
  <appliedjob>
    <total>1</total>
    <strjo>221</strjo>
  </appliedjob>
</information>
