<?xml version="1.0" encoding="UTF-8"?>
<information>
  <userinfo>
    <db>
      <id>5425</id>
      <email>Thangkientai@gmail.com</email>
      <username/>
      <name>Hiền</name>
      <im/>
      <gender>0</gender>
      <phone>0902652547</phone>
      <address/>
      <city>0</city>
      <dob>0000-00-00</dob>
      <type>1</type>
      <status>2</status>
      <created>1475975153</created>
      <dayleft>1478567153</dayleft>
      <page>1</page>
      <is_received_email>1</is_received_email>
      <last_signin>1475975153</last_signin>
      <jobleft>5</jobleft>
    </db>
  </userinfo>
</information>
