<?xml version="1.0" encoding="UTF-8"?>
<information>
  <userinfo>
    <db>
      <id>5838</id>
      <email>Bachcuc179@gmail.com</email>
      <username/>
      <name>Lương Thị Bạch Cúc</name>
      <im/>
      <gender>2</gender>
      <phone>01687219862</phone>
      <address>112/16 khu phố 11,đường Tân Chánh Hiệp 08,q12</address>
      <city>30</city>
      <dob>1998-7-1</dob>
      <type>2</type>
      <status>1</status>
      <created>1476203070</created>
      <dayleft>0</dayleft>
      <page>0</page>
      <is_received_email>0</is_received_email>
      <last_signin>1476203070</last_signin>
      <day>1</day>
      <month>7</month>
      <year>1998</year>
      <country>vn</country>
      <skype/>
      <facebook/>
      <is_newletter>0</is_newletter>
      <fb_load_newfeed>1</fb_load_newfeed>
      <fb_load_photo>1</fb_load_photo>
      <city_text_vi>Hồ Chí Minh</city_text_vi>
      <city_text_en>Ho Chi Minh City</city_text_en>
      <lat>10.8230989</lat>
      <lng>106.6296638</lng>
    </db>
  </userinfo>
  <user_cv>
    <db>
      <ui>5838</ui>
      <title>Nhân viên bán hàng</title>
      <experience>1</experience>
      <category>15,35</category>
      <type>2</type>
      <level>2</level>
      <lang>vi</lang>
      <s1>2</s1>
      <salary>1</salary>
      <about>Nhanh nhẹn,siêng năng. Đã từng làm việc và tiếp xúc với nhiều khách hàng nên có kinh nghiệm trong giao tiếp</about>
      <skill>Nhanh nhẹn,lanh lợi, hòa đồng,tiếp thu nhanh</skill>
      <keyword/>
    </db>
  </user_cv>
  <appliedjob>
    <total>1</total>
    <strjo>205</strjo>
  </appliedjob>
  <savedjob>
    <total>1</total>
    <strjo>205</strjo>
  </savedjob>
</information>
