<?xml version="1.0" encoding="UTF-8"?>
<information>
  <userinfo>
    <db>
      <id>6458</id>
      <email>Dieuhien2885@gmail.com</email>
      <username/>
      <name>Võ thị diệu hiền</name>
      <im/>
      <gender>0</gender>
      <phone>0938183638</phone>
      <address/>
      <city>0</city>
      <dob>0000-00-00</dob>
      <type>1</type>
      <status>2</status>
      <created>1476615225</created>
      <dayleft>1479207225</dayleft>
      <page>1</page>
      <is_received_email>1</is_received_email>
      <last_signin>1476615225</last_signin>
      <jobleft>5</jobleft>
    </db>
  </userinfo>
</information>
