<?xml version="1.0" encoding="UTF-8"?>
<information>
  <userinfo>
    <db>
      <id>6774</id>
      <email>Kimkhanh030398@mail.com</email>
      <username/>
      <name>Huỳnh Vũ Kim Khánh</name>
      <im>1476856181_huynh-vu-kim-khanh.png</im>
      <gender>2</gender>
      <phone>01685734777</phone>
      <address>489a/19 huỳnh văn bánh f13 q.phu nhuận</address>
      <city/>
      <dob>1998-3-3</dob>
      <type>2</type>
      <status>1</status>
      <created>1476856181</created>
      <dayleft>0</dayleft>
      <page>0</page>
      <day>3</day>
      <month>3</month>
      <year>1998</year>
      <country>vn</country>
      <skype/>
      <facebook/>
      <is_newletter>0</is_newletter>
      <is_received_email>0</is_received_email>
      <fb_load_newfeed>1</fb_load_newfeed>
      <fb_load_photo>1</fb_load_photo>
    </db>
  </userinfo>
  <user_cv>
    <db>
      <title>Pha chế</title>
      <experience>1</experience>
      <category>14,15</category>
      <type>4</type>
      <level>2</level>
      <lang>vi</lang>
      <skill>Phục  vụ và pha chế</skill>
      <ui>6774</ui>
      <s1>0</s1>
      <salary>1</salary>
      <about/>
      <keyword/>
    </db>
  </user_cv>
  <appliedjob>
    <total>4</total>
    <strjo>106,364,335,130</strjo>
  </appliedjob>
</information>
