<?xml version="1.0" encoding="UTF-8"?>
<information>
  <userinfo>
    <db>
      <id>6825</id>
      <email>ngocdiem6398@gmail.com</email>
      <username/>
      <name>Diễm Ngọc</name>
      <im>6825_14606344-711791082320041-6923160486327153158-n.jpg</im>
      <gender>2</gender>
      <dob>1998-3-6</dob>
      <deactive>0</deactive>
      <type>2</type>
      <status>1</status>
      <created>1476873673</created>
      <day>6</day>
      <month>3</month>
      <year>1998</year>
      <phone>0919303940</phone>
      <address>140/58 Điện Biên Phủ, Quận Bình Thạnh, Hồ Chí Minh,  Việt Nam</address>
      <country>vn</country>
      <city>30</city>
      <skype/>
      <facebook/>
      <is_newletter>0</is_newletter>
      <is_received_email>0</is_received_email>
      <fb_load_newfeed>1</fb_load_newfeed>
      <fb_load_photo>1</fb_load_photo>
      <city_text_vi>Hồ Chí Minh</city_text_vi>
      <city_text_en>Ho Chi Minh City</city_text_en>
      <lat>10.795966</lat>
      <lng>106.7034307</lng>
    </db>
  </userinfo>
  <user_cv>
    <db>
      <ui>6825</ui>
      <title>Nhân viên phục vụ, Pha chế, Lễ tân.</title>
      <experience>7</experience>
      <category>14,15,20,26,30</category>
      <type>2</type>
      <level>2</level>
      <lang>vi,en</lang>
      <s1>3000000</s1>
      <salary>1</salary>
      <about>Em vừa mới tốt nghiệp trung học phổ thông tại trường Chuyên Thăng Long Đà Lạt. Hiện giờ em đang trong giai đoạn gap year để chuẩn bị 2 năm sau đi du học. Em đang học tiếng Đức tại Deutsch Zentrum. Đến với thue.today, em rất muốn thử sức mình với các công việc bán thời gian. Em hòa đồng, tràn đầy tinh thần nhiệt huyết và rất muốn giao lưu, học hỏi kinh nghiệm từ mọi người xung quanh. Em có thể nói được một ít tiếng Đức và tiếng Anh. Với tính trung thực và chăm chỉ, em tin là mình có thể tìm được một công việc phù hợp và hoàn thành tốt công việc đó.</about>
      <skill>- Kỹ năng giao tiếp với mọi người&#13;
- Chăm chỉ, linh hoạt trong mọi công việc</skill>
      <keyword/>
    </db>
  </user_cv>
  <appliedjob>
    <total>1</total>
    <strjo>332</strjo>
  </appliedjob>
</information>
