<?xml version="1.0" encoding="UTF-8"?>
<information>
  <userinfo>
    <db>
      <id>7017</id>
      <email>thuyntp@trungnguyen.com.vn</email>
      <username/>
      <name>CHI NHÁNH CÔNG TY CỔ PHẦN TRUNG NGUYÊN FRANCHISING</name>
      <im/>
      <gender>0</gender>
      <phone>0977880087</phone>
      <address>hrtnf@trungnguyen.com.vn</address>
      <city>0</city>
      <dob>0000-00-00</dob>
      <type>1</type>
      <status>2</status>
      <created>1477020296</created>
      <dayleft>1479612296</dayleft>
      <jobleft>5</jobleft>
      <page>1</page>
      <is_received_email>1</is_received_email>
      <last_signin>1477020296</last_signin>
    </db>
  </userinfo>
  <totalJob>
    <total>1</total>
    <strji>505</strji>
  </totalJob>
</information>
