<?xml version="1.0" encoding="UTF-8"?>
<information>
  <userinfo>
    <db>
      <id>7610</id>
      <email>thanhtan931998@yahoo.com</email>
      <username></username>
      <name>Thành Tấn</name>
      <im>1851105888452375_thanh-tan.jpg</im>
      <gender>1</gender>
      <dob>0000-00-00</dob>
      <deactive>0</deactive>
      <type>2</type>
      <status>1</status>
      <created>1477327851</created>
      <day>0</day>
      <month>0</month>
      <year>0</year>
    </db>
  </userinfo>
</information>
